helm_analytics/__init__.py
helm_analytics/middleware.py
helm_analytics-5.0.0.dist-info/METADATA
helm_analytics-5.0.0.dist-info/WHEEL
helm_analytics-5.0.0.dist-info/top_level.txt
helm_analytics-5.0.0.dist-info/RECORD
