Metadata-Version: 2.1
Name: helm-analytics
Version: 5.0.0
Summary: Official Python SDK for Helm Analytics
Home-page: https://github.com/Helm-Analytics/sentinel-mvp/tree/main/sdk/python
Author: Helm Analytics
Author-email: support@helm-analytics.com
Classifier: Programming Language :: Python :: 3
Classifier: License :: OSI Approved :: Apache Software License
Classifier: Operating System :: OS Independent
Classifier: Framework :: FastAPI
Classifier: Framework :: Flask
Classifier: Framework :: Django
Requires-Python: >=3.6
Requires-Dist: requests>=2.25.0
Provides-Extra: fastapi
Requires-Dist: fastapi; extra == "fastapi"
Requires-Dist: uvicorn; extra == "fastapi"
